codegenlib/__init__.py
codegenlib/abstract.py
codegenlib/constantType.py
codegenlib/enums.py
codegenlib/environment.py
codegenlib/fileOperation.py
codegenlib/httpOperation.py
codegenlib/httpOperation3.py
codegenlib/log.py
codegenlib/parser.py
codegenlib/singleton.py
codegenlib/templateFile.py
codegenlib/templateFolder.py
codegenlib/templateModule.py
codegenlib/templateStreaming.py
codegenlib-0.8.0.dist-info/LICENSE
codegenlib-0.8.0.dist-info/METADATA
codegenlib-0.8.0.dist-info/WHEEL
codegenlib-0.8.0.dist-info/top_level.txt
codegenlib-0.8.0.dist-info/RECORD
