Metadata-Version: 2.1
Name: codegenlib
Version: 0.8.0
Summary: Code Generation library written by python. can use bash script, can be extend python code, can use mustache files or can use any string content for any code generation structure.
Home-page: https://github.com/umutboz/code-gen-lib
Author: Umut Boz
Author-email: umut.boz@outlook.com
Project-URL: Documentation, https://github.com/umutboz/code-gen-lib
Project-URL: Bug Reports, https://github.com/umutboz/code-gen-lib/issues
Project-URL: Source Code, https://github.com/umutboz/code-gen-lib
Keywords: code generation,file generation,pypi,package
Classifier: Development Status :: 5 - Production/Stable
Classifier: Intended Audience :: Developers
Classifier: Topic :: Software Development :: Build Tools
Classifier: Programming Language :: Python :: 2.7
Classifier: Programming Language :: Python :: 3
Classifier: Programming Language :: Python :: 3.6
Classifier: Programming Language :: Python :: 3.7
Classifier: Programming Language :: Python :: 3.8
Classifier: Programming Language :: Python :: 3.9
Classifier: License :: OSI Approved :: MIT License
Classifier: Operating System :: OS Independent
Requires-Python: >=2.7
License-File: LICENSE
Provides-Extra: dev
Requires-Dist: check-manifest ; extra == 'dev'
